intercode/__init__.py
intercode/assets/__init__.py
intercode/assets/datasets/__init__.py
intercode/assets/datasets/bash_queries.json
intercode/assets/datasets/spider_dev.sql
intercode/assets/datasets/sql_queries.csv
intercode/assets/docker/__init__.py
intercode/assets/docker/bash.Dockerfile
intercode/assets/docker/docker.gitignore
intercode/assets/docker/setup_fs.sh
intercode/assets/docker/sql-docker-compose.yml
intercode/assets/docker/sql.Dockerfile
intercode/envs/__init__.py
intercode/envs/ic_env.py
intercode/envs/bash/__init__.py
intercode/envs/bash/bash_env.py
intercode/envs/game/__init__.py
intercode/envs/game/ctf_env.py
intercode/envs/sql/__init__.py
intercode/envs/sql/sql_env.py
intercode/utils/__init__.py
intercode/utils/data_loader.py
intercode/utils/utils.py
intercode_bench-0.1.22.dist-info/LICENSE
intercode_bench-0.1.22.dist-info/METADATA
intercode_bench-0.1.22.dist-info/WHEEL
intercode_bench-0.1.22.dist-info/top_level.txt
intercode_bench-0.1.22.dist-info/RECORD
