Metadata-Version: 2.1
Name: intercode-bench
Version: 0.1.22
Summary: The official InterCode benchmark package - a framework for interactive code tasks
Home-page: http://github.com/intercode-benchmark/intercode-benchmark
Author: John Yang
Author-email: byjohnyang@gmail.com
Project-URL: Documentation, https://github.com/intercode-benchmark/intercode-benchmark
Project-URL: Bug Reports, https://github.com/intercode-benchmark/intercode-benchmark/issues
Project-URL: Source Code, https://github.com/intercode-benchmark/intercode-benchmark
Project-URL: Website, https://intercode-benchmark.github.io/
Keywords: nlp,benchmark,interaction,code,rl,decision making
Classifier: Programming Language :: Python :: 3.8
Classifier: Programming Language :: Python :: 3.9
Classifier: Programming Language :: Python :: 3 :: Only
Classifier: License :: OSI Approved :: MIT License
Classifier: Operating System :: OS Independent
Requires-Python: >=3.8
License-File: LICENSE
Requires-Dist: gymnasium
Requires-Dist: mysql-connector-python
Requires-Dist: scikit-learn (>=1.2.2)
Requires-Dist: pandas
Requires-Dist: rich
Requires-Dist: docker
